{
  "council": "NERC",
  "count_of_applications": "43",
  "count_of_awards": "24",
  "year": "2016",
  "applications": [
    {
      "outcome": "Successful",
      "application_id": "NE/P017436/1",
      "rank": "1"
    },
    {
      "outcome": "Successful",
      "application_id": "NE/P01738X/1",
      "rank": "2"
    },
    {
      "outcome": "Successful",
      "application_id": "NE/P017061/1",
      "rank": "2"
    },
    {
      "outcome": "Successful",
      "application_id": "NE/P017185/1",
      "rank": "2"
    },
    {
      "outcome": "Successful",
      "application_id": "NE/P017274/1",
      "rank": "2"
    },
    {
      "outcome": "Successful",
      "application_id": "NE/P017347/1",
      "rank": "2"
    },
    {
      "outcome": "Successful",
      "application_id": "NE/P017134/1",
      "rank": "3"
    },
    {
      "outcome": "Successful",
      "application_id": "NE/P017231/1",
      "rank": "4"
    },
    {
      "outcome": "Successful",
      "application_id": "NE/P016693/1",
      "rank": "4"
    },
    {
      "outcome": "Successful",
      "application_id": "NE/P016715/1",
      "rank": "4"
    },
    {
      "outcome": "Successful",
      "application_id": "NE/P016758/1",
      "rank": "4"
    },
    {
      "outcome": "Successful",
      "application_id": "NE/P016782/1",
      "rank": "4"
    },
    {
      "outcome": "Successful",
      "application_id": "NE/P016863/1",
      "rank": "4"
    },
    {
      "outcome": "Successful",
      "application_id": "NE/P016928/1",
      "rank": "4"
    },
    {
      "outcome": "Successful",
      "application_id": "NE/P017142/1",
      "rank": "4"
    },
    {
      "outcome": "Successful",
      "application_id": "NE/P017150/1",
      "rank": "4"
    },
    {
      "outcome": "Successful",
      "application_id": "NE/P017290/1",
      "rank": "4"
    },
    {
      "outcome": "Successful",
      "application_id": "NE/P017452/1",
      "rank": "5"
    },
    {
      "outcome": "Successful",
      "application_id": "NE/P017045/1",
      "rank": "5"
    },
    {
      "outcome": "Successful",
      "application_id": "NE/P017053/1",
      "rank": "5"
    },
    {
      "outcome": "Successful",
      "application_id": "NE/P01724X/1",
      "rank": "5"
    },
    {
      "outcome": "Successful",
      "application_id": "NE/P017312/1",
      "rank": "5"
    },
    {
      "outcome": "Successful",
      "application_id": "NE/P017371/1",
      "rank": "5"
    },
    {
      "outcome": "Successful",
      "application_id": "NE/P017444/1",
      "rank": "5"
    },
    {
      "outcome": "Unsuccessful",
      "application_id": "NE/P01707X/1",
      "rank": "6"
    },
    {
      "outcome": "Unsuccessful",
      "application_id": "NE/P016847/1",
      "rank": "6"
    },
    {
      "outcome": "Unsuccessful",
      "application_id": "NE/P017088/1",
      "rank": "6"
    },
    {
      "outcome": "Unsuccessful",
      "application_id": "NE/P017355/1",
      "rank": "7"
    },
    {
      "outcome": "Unsuccessful",
      "application_id": "NE/P017126/1",
      "rank": "7"
    },
    {
      "outcome": "Unsuccessful",
      "application_id": "NE/P017169/1",
      "rank": "7"
    },
    {
      "outcome": "Unsuccessful",
      "application_id": "NE/P017207/1",
      "rank": "7"
    },
    {
      "outcome": "Unsuccessful",
      "application_id": "NE/P017215/1",
      "rank": "7"
    },
    {
      "outcome": "Unsuccessful",
      "application_id": "NE/P017223/1",
      "rank": "7"
    },
    {
      "outcome": "Unsuccessful",
      "application_id": "NE/P017282/1",
      "rank": "7"
    },
    {
      "outcome": "Unsuccessful",
      "application_id": "NE/P017304/1",
      "rank": "85"
    },
    {
      "outcome": "Unsuccessful",
      "application_id": "NE/P017398/1",
      "rank": "785"
    },
    {
      "outcome": "Unsuccessful",
      "application_id": "NE/P017460/1",
      "rank": "875"
    },
    {
      "outcome": "Unsuccessful",
      "application_id": "NE/P017495/1",
      "rank": "4"
    },
    {
      "outcome": "Unsuccessful",
      "application_id": "NE/P017487/1",
      "rank": "74"
    },
    {
      "outcome": "Unsuccessful",
      "application_id": "NE/P017363/1",
      "rank": "1074"
    },
    {
      "outcome": "Unsuccessful",
      "application_id": "NE/P017428/1",
      "rank": "1074"
    },
    {
      "outcome": "Unsuccessful",
      "application_id": "NE/P017258/1",
      "rank": "1174"
    },
    {
      "outcome": "Unsuccessful",
      "application_id": "NE/P017479/1",
      "rank": "4"
    }
  ],
  "meeting_name": "Highlight Topics September 2016",
  "source": "Highlight Topics Sept 2016.pdf",
  "meeting_start": "2016",
  "meeting_end": "2016"
}