{
  "council": "EPSRC",
  "meeting_reference": "PAN954",
  "meeting_name": "EPSRC Engineering Prioritisation Panel February 2025 – Open Fellowships (Old)",
  "meeting_convenor": "H Minter",
  "applications": [
    {
      "application_id": "APP7913",
      "title": "",
      "lead_organisation": "",
      "outcome": "Unsuccessful",
      "rank": "1",
      "rank_group": "Ranked",
      "awarded_amount": "",
      "award_id": "",
      "opportunity_number": "139",
      "lead_applicant": "",
      "link": "",
      "opportunity": "EPSRC open fellowship May 2023"
    }
  ],
  "source": "https://public.tableau.com/app/profile/epsrcdatateam/viz/EPSRCFundingApplicationOutcomes/MeetingList",
  "meeting_start": "2025-02-04",
  "meeting_end": "2025-02-04"
}