{
  "council": "EPSRC",
  "meeting_reference": "PAN1124",
  "meeting_name": "EPSRC Engineering and Energy Fellowships Interview Panel May 2025 - Open Fellowship",
  "meeting_date": "2025-05-07 08:00:00",
  "meeting_convenor": "Calderon Munoz, Dr M",
  "applications": [
    {
      "application_id": "APP34578",
      "title": "Offshore Wind Infrastructure Design Evolution with Provision for Life Extension (WIND-PROLIFE)",
      "applicant": "Mehmanparast, A",
      "lead_organisation": "University of Strathclyde",
      "outcome": "Funded",
      "rank": "",
      "rank_group": "Unranked",
      "awarded_amount": "1396025.12",
      "award_id": "UKRI3801",
      "hyperlink": "https://gtr.ukri.org/projects?ref=3801",
      "list_name": "Main",
      "opportunity_number": "297",
      "opportunity_name": "EPSRC open fellowships, Dec 2023: responsive mode"
    }
  ]
}