{
  "council": "AHRC",
  "source": "tfs",
  "meeting_name": "OPP190: AHRC: BRAID: Scoping to Embed Responsible AI in Context",
  "applications": [
    {
      "application_id": "11615",
      "title": "",
      "score": "8",
      "status_label": "Status",
      "outcome": "Unsuccessful",
      "lead_applicant": "",
      "lead_organisation": "",
      "rank": "11"
    },
    {
      "application_id": "18134",
      "title": "",
      "score": "8",
      "status_label": "Status",
      "outcome": "Unsuccessful",
      "lead_applicant": "",
      "lead_organisation": "",
      "rank": "12"
    },
    {
      "application_id": "18538",
      "title": "",
      "score": "8",
      "status_label": "Status",
      "outcome": "Unsuccessful",
      "lead_applicant": "",
      "lead_organisation": "",
      "rank": "13"
    },
    {
      "application_id": "16453",
      "title": "",
      "score": "8",
      "status_label": "Status",
      "outcome": "Unsuccessful",
      "lead_applicant": "",
      "lead_organisation": "",
      "rank": "14"
    },
    {
      "application_id": "12769",
      "title": "",
      "score": "7",
      "status_label": "Status",
      "outcome": "Unsuccessful",
      "lead_applicant": "",
      "lead_organisation": "",
      "rank": "15"
    },
    {
      "application_id": "17136",
      "title": "",
      "score": "7",
      "status_label": "Status",
      "outcome": "Unsuccessful",
      "lead_applicant": "",
      "lead_organisation": "",
      "rank": "16"
    },
    {
      "application_id": "12928",
      "title": "",
      "score": "7",
      "status_label": "Status",
      "outcome": "Unsuccessful",
      "lead_applicant": "",
      "lead_organisation": "",
      "rank": "17"
    },
    {
      "application_id": "13091",
      "title": "",
      "score": "7",
      "status_label": "Status",
      "outcome": "Unsuccessful",
      "lead_applicant": "",
      "lead_organisation": "",
      "rank": "18"
    },
    {
      "application_id": "16306",
      "title": "",
      "score": "7",
      "status_label": "Status",
      "outcome": "Unsuccessful",
      "lead_applicant": "",
      "lead_organisation": "",
      "rank": "19"
    },
    {
      "application_id": "17594",
      "title": "",
      "score": "7",
      "status_label": "Status",
      "outcome": "Unsuccessful",
      "lead_applicant": "",
      "lead_organisation": "",
      "rank": "20"
    },
    {
      "application_id": "10592",
      "title": "",
      "score": "7",
      "status_label": "Status",
      "outcome": "Unsuccessful",
      "lead_applicant": "",
      "lead_organisation": "",
      "rank": "21"
    },
    {
      "application_id": "15148",
      "title": "",
      "score": "7",
      "status_label": "Status",
      "outcome": "Unsuccessful",
      "lead_applicant": "",
      "lead_organisation": "",
      "rank": "22"
    },
    {
      "application_id": "19267",
      "title": "",
      "score": "7",
      "status_label": "Status",
      "outcome": "Unsuccessful",
      "lead_applicant": "",
      "lead_organisation": "",
      "rank": "23"
    },
    {
      "application_id": "19091",
      "title": "",
      "score": "6",
      "status_label": "Status",
      "outcome": "Unsuccessful",
      "lead_applicant": "",
      "lead_organisation": "",
      "rank": "24"
    },
    {
      "application_id": "18786",
      "title": "",
      "score": "6",
      "status_label": "Status",
      "outcome": "Unsuccessful",
      "lead_applicant": "",
      "lead_organisation": "",
      "rank": "25"
    },
    {
      "application_id": "18209",
      "title": "",
      "score": "6",
      "status_label": "Status",
      "outcome": "Unsuccessful",
      "lead_applicant": "",
      "lead_organisation": "",
      "rank": "26"
    },
    {
      "application_id": "17867",
      "title": "",
      "score": "6",
      "status_label": "Status",
      "outcome": "Unsuccessful",
      "lead_applicant": "",
      "lead_organisation": "",
      "rank": "27"
    },
    {
      "application_id": "16190",
      "title": "",
      "score": "6",
      "status_label": "Status",
      "outcome": "Unsuccessful",
      "lead_applicant": "",
      "lead_organisation": "",
      "rank": "28"
    },
    {
      "application_id": "13907",
      "title": "",
      "score": "6",
      "status_label": "Status",
      "outcome": "Unsuccessful",
      "lead_applicant": "",
      "lead_organisation": "",
      "rank": "29"
    },
    {
      "application_id": "19086",
      "title": "",
      "score": "6",
      "status_label": "Status",
      "outcome": "Unsuccessful",
      "lead_applicant": "",
      "lead_organisation": "",
      "rank": "30"
    },
    {
      "application_id": "16805",
      "title": "Shared Post-Human Imagination: Human-AI Collaboration in Media Creation",
      "score": "9",
      "status_label": "Status",
      "outcome": "Successful",
      "lead_applicant": "Szilvia Ruszev",
      "lead_organisation": "Bournemouth University",
      "rank": "1"
    },
    {
      "application_id": "17938",
      "title": "Museum Visitor Experience and the Responsible Use of AI to Communicate Colonial Collections",
      "score": "9",
      "status_label": "Status",
      "outcome": "Successful",
      "lead_applicant": "Joanna Tidy",
      "lead_organisation": "University of Sheffield",
      "rank": "2"
    },
    {
      "application_id": "15439",
      "title": "\"Ethical Review to Support Responsible AI in Policing - A Preliminary Study of West Midlands Police's Specialist Data Ethics Review Committee \"",
      "score": "9",
      "status_label": "Status",
      "outcome": "Successful",
      "lead_applicant": "Marion Oswald",
      "lead_organisation": "Northumbria University",
      "rank": "3"
    },
    {
      "application_id": "18206",
      "title": "Creating a Dynamic Archive of Responsible Ecosystems in the Context of Creative AI",
      "score": "9",
      "status_label": "Status",
      "outcome": "Successful",
      "lead_applicant": "Lydia Farina",
      "lead_organisation": "University of Nottingham",
      "rank": "4"
    },
    {
      "application_id": "17294",
      "title": "iREAL: Inclusive Requirements Elicitation for AI in Libraries to Support Respectful Management of Indigenous Knowledges",
      "score": "8",
      "status_label": "Status",
      "outcome": "Successful",
      "lead_applicant": "Paul Gooding",
      "lead_organisation": "University of Glasgow",
      "rank": "5"
    },
    {
      "application_id": "19168",
      "title": "Towards Embedding Responsible AI in the School System: Co-Creation with Young People",
      "score": "8",
      "status_label": "Status",
      "outcome": "Successful",
      "lead_applicant": "Judy Robertson",
      "lead_organisation": "University of Edinburgh",
      "rank": "6"
    },
    {
      "application_id": "12840",
      "title": "\"AI in the Street: Scoping Everyday Observatories for Public Engagement with Connected and Automated Urban Environments\"",
      "score": "8",
      "status_label": "Status",
      "outcome": "Successful",
      "lead_applicant": "Noortje Suzanne Marres",
      "lead_organisation": "University of Warwick",
      "rank": "7"
    },
    {
      "application_id": "17685",
      "title": "\"CREAATIF: Crafting Responsive Assessments of AI and Tech-Impacted Futures\"",
      "score": "8",
      "status_label": "Status",
      "outcome": "Successful",
      "lead_applicant": "David Leslie",
      "lead_organisation": "Queen Mary University of London",
      "rank": "8"
    },
    {
      "application_id": "13917",
      "title": "FRAIM: Framing Responsible AI Implementation and Management",
      "score": "8",
      "status_label": "Status",
      "outcome": "Successful",
      "lead_applicant": "Denis Newman-Griffis",
      "lead_organisation": "University of Sheffield",
      "rank": "9"
    },
    {
      "application_id": "11259",
      "title": "Trustworthy and Ethical Assurance of Digital Twins (TEA-DT)",
      "score": "8",
      "status_label": "Status",
      "outcome": "Successful",
      "lead_applicant": "Christopher Burr",
      "lead_organisation": "The Alan Turing Institute",
      "rank": "10"
    },
    {
      "application_id": "19076",
      "title": "",
      "score": "5",
      "status_label": "Status",
      "outcome": "Unsuccessful",
      "lead_applicant": "",
      "lead_organisation": "",
      "rank": ""
    },
    {
      "application_id": "18730",
      "title": "",
      "score": "5",
      "status_label": "Status",
      "outcome": "Unsuccessful",
      "lead_applicant": "",
      "lead_organisation": "",
      "rank": ""
    },
    {
      "application_id": "18311",
      "title": "",
      "score": "5",
      "status_label": "Status",
      "outcome": "Unsuccessful",
      "lead_applicant": "",
      "lead_organisation": "",
      "rank": ""
    },
    {
      "application_id": "18070",
      "title": "",
      "score": "5",
      "status_label": "Status",
      "outcome": "Unsuccessful",
      "lead_applicant": "",
      "lead_organisation": "",
      "rank": ""
    },
    {
      "application_id": "14160",
      "title": "",
      "score": "5",
      "status_label": "Status",
      "outcome": "Unsuccessful",
      "lead_applicant": "",
      "lead_organisation": "",
      "rank": ""
    },
    {
      "application_id": "19314",
      "title": "",
      "score": "5",
      "status_label": "Status",
      "outcome": "Unsuccessful",
      "lead_applicant": "",
      "lead_organisation": "",
      "rank": ""
    },
    {
      "application_id": "8913",
      "title": "",
      "score": "5",
      "status_label": "Status",
      "outcome": "Unsuccessful",
      "lead_applicant": "",
      "lead_organisation": "",
      "rank": ""
    },
    {
      "application_id": "9959",
      "title": "",
      "score": "4",
      "status_label": "Status",
      "outcome": "Unsuccessful",
      "lead_applicant": "",
      "lead_organisation": "",
      "rank": ""
    }
  ],
  "panellists": [
    {
      "name": "Katharine Willis",
      "organisation": "Unknown",
      "role": "Chair"
    },
    {
      "name": "Adrian Hilton",
      "organisation": "Unknown",
      "role": "Panellist"
    },
    {
      "name": "Andrew McStay",
      "organisation": "Unknown",
      "role": "Panellist"
    },
    {
      "name": "Chara Bakalis",
      "organisation": "Unknown",
      "role": "Panellist"
    },
    {
      "name": "Christopher Yau",
      "organisation": "Unknown",
      "role": "Panellist"
    },
    {
      "name": "Jessica Rushworth",
      "organisation": "Unknown",
      "role": "Panellist"
    },
    {
      "name": "Johnny Golding",
      "organisation": "Unknown",
      "role": "Panellist"
    },
    {
      "name": "Kaska Porayska-Pomsta",
      "organisation": "Unknown",
      "role": "Panellist"
    },
    {
      "name": "Mabrouka Abuhmida",
      "organisation": "Unknown",
      "role": "Panellist"
    },
    {
      "name": "TonyMcEnery",
      "organisation": "Unknown",
      "role": "Panellist"
    }
  ]
}